desec/__init__.py
desec/models.py
desec-0.0.3.dist-info/LICENSE
desec-0.0.3.dist-info/METADATA
desec-0.0.3.dist-info/WHEEL
desec-0.0.3.dist-info/top_level.txt
desec-0.0.3.dist-info/RECORD
