Metadata-Version: 2.1
Name: desec
Version: 0.0.3
Summary: desec.io python client
Author-email: Freerk-Ole Zakfeld <freerk@zakfeld.com>
License: MIT License
Project-URL: Homepage, https://github.com/fzakfeld/desec-python
Project-URL: Bug Tracker, https://github.com/fzakfeld/desec-python/issues
Classifier: Programming Language :: Python :: 3
Classifier: License :: OSI Approved :: MIT License
Classifier: Operating System :: OS Independent
Requires-Python: >=3.7
License-File: LICENSE
